smartmind_image/__init__.py
smartmind_image/image_quadtree.py
smartmind_image-0.0.3.dist-info/METADATA
smartmind_image-0.0.3.dist-info/WHEEL
smartmind_image-0.0.3.dist-info/top_level.txt
smartmind_image-0.0.3.dist-info/RECORD
